cap_upload_validator/__init__.py
cap_upload_validator/__main__.py
cap_upload_validator/cli.py
cap_upload_validator/errors.py
cap_upload_validator/upload_validator.py
cap_upload_validator/gene_mapping/__init__.py
cap_upload_validator/gene_mapping/gene_map.py
cap_upload_validator/gene_mapping/data/homo_sapiens.csv
cap_upload_validator/gene_mapping/data/mus_musculus.csv
cap_upload_validator-1.5.1.dist-info/METADATA
cap_upload_validator-1.5.1.dist-info/WHEEL
cap_upload_validator-1.5.1.dist-info/entry_points.txt
cap_upload_validator-1.5.1.dist-info/licenses/LICENSE
cap_upload_validator-1.5.1.dist-info/RECORD
