Metadata-Version: 2.4
Name: cap_upload_validator
Version: 1.5.1
Summary: Python tool for validating H5AD AnnData files before uploading to the Cell Annotation Platform.
Project-URL: Homepage, https://celltype.info/
Project-URL: GitHub, https://github.com/cellannotation/cap-validator
Project-URL: Issues, https://github.com/cellannotation/cap-validator/issues
Project-URL: Changelog, https://github.com/cellannotation/cap-validator/blob/main/CHANGELOG.md
Project-URL: Documentation, https://github.com/cellannotation/cap-validator/wiki
Author: Roman Mukhin, Andrey Isaev, Evan Biederstedt
License-Expression: BSD-3-Clause
License-File: LICENSE
Classifier: Operating System :: OS Independent
Classifier: Programming Language :: Python :: 3
Requires-Python: >=3.9
Requires-Dist: cap-anndata>=0.5.0
Requires-Dist: numpy>=2.0.2
Requires-Dist: pandas>=2.2.3
Requires-Dist: scipy>=1.13.1
